databases_patched/__init__.py
databases_patched/core.py
databases_patched/importer.py
databases_patched/interfaces.py
databases_patched/py.typed
databases_patched/backends/__init__.py
databases_patched/backends/aiopg.py
databases_patched/backends/asyncmy.py
databases_patched/backends/mysql.py
databases_patched/backends/postgres.py
databases_patched/backends/sqlite.py
databases_patched/backends/common/__init__.py
databases_patched/backends/common/records.py
databases_patched/backends/compilers/__init__.py
databases_patched/backends/compilers/psycopg.py
databases_patched/backends/dialects/__init__.py
databases_patched/backends/dialects/psycopg.py
databases_patched-0.9.3.dist-info/LICENSE.md
databases_patched-0.9.3.dist-info/METADATA
databases_patched-0.9.3.dist-info/WHEEL
databases_patched-0.9.3.dist-info/top_level.txt
databases_patched-0.9.3.dist-info/RECORD
