Metadata-Version: 2.2
Name: databases-patched
Version: 0.9.3
Summary: Async database support for Python. (Custom Patched version, this is not the original version.)
License: BSD
Classifier: Development Status :: 3 - Alpha
Classifier: Environment :: Web Environment
Classifier: Intended Audience :: Developers
Classifier: License :: OSI Approved :: BSD License
Classifier: Operating System :: OS Independent
Classifier: Topic :: Internet :: WWW/HTTP
Classifier: Programming Language :: Python :: 3
Classifier: Programming Language :: Python :: 3.8
Classifier: Programming Language :: Python :: 3.9
Classifier: Programming Language :: Python :: 3.10
Classifier: Programming Language :: Python :: 3.11
Classifier: Programming Language :: Python :: 3.12
Classifier: Programming Language :: Python :: 3 :: Only
Requires-Python: >=3.8
License-File: LICENSE.md
Requires-Dist: sqlalchemy>=2.0.7
Provides-Extra: postgresql
Requires-Dist: asyncpg; extra == "postgresql"
Provides-Extra: asyncpg
Requires-Dist: asyncpg; extra == "asyncpg"
Provides-Extra: aiopg
Requires-Dist: aiopg; extra == "aiopg"
Provides-Extra: mysql
Requires-Dist: aiomysql; extra == "mysql"
Provides-Extra: aiomysql
Requires-Dist: aiomysql; extra == "aiomysql"
Provides-Extra: asyncmy
Requires-Dist: asyncmy; extra == "asyncmy"
Provides-Extra: sqlite
Requires-Dist: aiosqlite; extra == "sqlite"
Provides-Extra: aiosqlite
Requires-Dist: aiosqlite; extra == "aiosqlite"
Dynamic: classifier
Dynamic: description
Dynamic: description-content-type
Dynamic: license
Dynamic: provides-extra
Dynamic: requires-dist
Dynamic: requires-python
Dynamic: summary
